<?xml version="1.0" encoding="utf-8"?><PipeStats xmlns="http://pacificbiosciences.com/PacBioPipelineStats.xsd" xmlns:xsi="http://www.w3.org/2001/XMLSchema-instance" xmlns:ns="http://pacificbiosciences.com/PacBioBaseDataModel.xsd" Version="4.0.1"><MovieName>/data/pa/m64241e_240520_071340.baz</MovieName><MovieLength>5</MovieLength><NumSequencingZmws>8014671</NumSequencingZmws><NumFailedSnrFilterZmws>3</NumFailedSnrFilterZmws><NumFailedDmeZmws>0</NumFailedDmeZmws><TotalBaseFractionPerChannel Channel="A"><TotalBaseFractionValue>0.110258</TotalBaseFractionValue></TotalBaseFractionPerChannel><TotalBaseFractionPerChannel Channel="C"><TotalBaseFractionValue>0.0186506</TotalBaseFractionValue></TotalBaseFractionPerChannel><TotalBaseFractionPerChannel Channel="G"><TotalBaseFractionValue>0.6226</TotalBaseFractionValue></TotalBaseFractionPerChannel><TotalBaseFractionPerChannel Channel="T"><TotalBaseFractionValue>0.248491</TotalBaseFractionValue></TotalBaseFractionPerChannel><BaselineLevelDist Channel="A"><ns:SampleSize>11</ns:SampleSize><ns:SampleMean>7.9201</ns:SampleMean><ns:SampleMed>6.58984</ns:SampleMed><ns:SampleMode>5.71699</ns:SampleMode><ns:SampleStd>2.98976</ns:SampleStd><ns:Sample95thPct>14.5391</ns:Sample95thPct><ns:NumBins>30</ns:NumBins><ns:BinCounts><ns:BinCount>1</ns:BinCount><ns:BinCount>0</ns:BinCount><ns:BinCount>0</ns:BinCount><ns:BinCount>1</ns:BinCount><ns:BinCount>2</ns:BinCount><ns:BinCount>1</ns:BinCount><ns:BinCount>0</ns:BinCount><ns:BinCount>1</ns:BinCount><ns:BinCount>0</ns:BinCount><ns:BinCount>0</ns:BinCount><ns:BinCount>0</ns:BinCount><ns:BinCount>1</ns:BinCount><ns:BinCount>0</ns:BinCount><ns:BinCount>0</ns:BinCount><ns:BinCount>0</ns:BinCount><ns:BinCount>0</ns:BinCount><ns:BinCount>0</ns:BinCount><ns:BinCount>2</ns:BinCount><ns:BinCount>1</ns:BinCount><ns:BinCount>0</ns:BinCount><ns:BinCount>0</ns:BinCount><ns:BinCount>0</ns:BinCount><ns:BinCount>0</ns:BinCount><ns:BinCount>0</ns:BinCount><ns:BinCount>0</ns:BinCount><ns:BinCount>0</ns:BinCount><ns:BinCount>0</ns:BinCount><ns:BinCount>0</ns:BinCount><ns:BinCount>0</ns:BinCount><ns:BinCount>0</ns:BinCount></ns:BinCounts><ns:BinWidth>0.345964</ns:BinWidth><ns:MinOutlierValue>4.16016</ns:MinOutlierValue><ns:MinBinValue>4.16016</ns:MinBinValue><ns:MaxBinValue>14.5391</ns:MaxBinValue><ns:MaxOutlierValue>14.5391</ns:MaxOutlierValue><ns:MetricDescription>Baseline Level: Channel A</ns:MetricDescription></BaselineLevelDist><BaselineLevelDist Channel="C"><ns:SampleSize>11</ns:SampleSize><ns:SampleMean>7.9201</ns:SampleMean><ns:SampleMed>6.58984</ns:SampleMed><ns:SampleMode>5.71699</ns:SampleMode><ns:SampleStd>2.98976</ns:SampleStd><ns:Sample95thPct>14.5391</ns:Sample95thPct><ns:NumBins>30</ns:NumBins><ns:BinCounts><ns:BinCount>1</ns:BinCount><ns:BinCount>0</ns:BinCount><ns:BinCount>0</ns:BinCount><ns:BinCount>1</ns:BinCount><ns:BinCount>2</ns:BinCount><ns:BinCount>1</ns:BinCount><ns:BinCount>0</ns:BinCount><ns:BinCount>1</ns:BinCount><ns:BinCount>0</ns:BinCount><ns:BinCount>0</ns:BinCount><ns:BinCount>0</ns:BinCount><ns:BinCount>1</ns:BinCount><ns:BinCount>0</ns:BinCount><ns:BinCount>0</ns:BinCount><ns:BinCount>0</ns:BinCount><ns:BinCount>0</ns:BinCount><ns:BinCount>0</ns:BinCount><ns:BinCount>2</ns:BinCount><ns:BinCount>1</ns:BinCount><ns:BinCount>0</ns:BinCount><ns:BinCount>0</ns:BinCount><ns:BinCount>0</ns:BinCount><ns:BinCount>0</ns:BinCount><ns:BinCount>0</ns:BinCount><ns:BinCount>0</ns:BinCount><ns:BinCount>0</ns:BinCount><ns:BinCount>0</ns:BinCount><ns:BinCount>0</ns:BinCount><ns:BinCount>0</ns:BinCount><ns:BinCount>0</ns:BinCount></ns:BinCounts><ns:BinWidth>0.345964</ns:BinWidth><ns:MinOutlierValue>4.16016</ns:MinOutlierValue><ns:MinBinValue>4.16016</ns:MinBinValue><ns:MaxBinValue>14.5391</ns:MaxBinValue><ns:MaxOutlierValue>14.5391</ns:MaxOutlierValue><ns:MetricDescription>Baseline Level: Channel C</ns:MetricDescription></BaselineLevelDist><BaselineLevelDist Channel="G"><ns:SampleSize>11</ns:SampleSize><ns:SampleMean>7.9201</ns:SampleMean><ns:SampleMed>6.58984</ns:SampleMed><ns:SampleMode>5.71699</ns:SampleMode><ns:SampleStd>2.98976</ns:SampleStd><ns:Sample95thPct>14.5391</ns:Sample95thPct><ns:NumBins>30</ns:NumBins><ns:BinCounts><ns:BinCount>1</ns:BinCount><ns:BinCount>0</ns:BinCount><ns:BinCount>0</ns:BinCount><ns:BinCount>1</ns:BinCount><ns:BinCount>2</ns:BinCount><ns:BinCount>1</ns:BinCount><ns:BinCount>0</ns:BinCount><ns:BinCount>1</ns:BinCount><ns:BinCount>0</ns:BinCount><ns:BinCount>0</ns:BinCount><ns:BinCount>0</ns:BinCount><ns:BinCount>1</ns:BinCount><ns:BinCount>0</ns:BinCount><ns:BinCount>0</ns:BinCount><ns:BinCount>0</ns:BinCount><ns:BinCount>0</ns:BinCount><ns:BinCount>0</ns:BinCount><ns:BinCount>2</ns:BinCount><ns:BinCount>1</ns:BinCount><ns:BinCount>0</ns:BinCount><ns:BinCount>0</ns:BinCount><ns:BinCount>0</ns:BinCount><ns:BinCount>0</ns:BinCount><ns:BinCount>0</ns:BinCount><ns:BinCount>0</ns:BinCount><ns:BinCount>0</ns:BinCount><ns:BinCount>0</ns:BinCount><ns:BinCount>0</ns:BinCount><ns:BinCount>0</ns:BinCount><ns:BinCount>0</ns:BinCount></ns:BinCounts><ns:BinWidth>0.345964</ns:BinWidth><ns:MinOutlierValue>4.16016</ns:MinOutlierValue><ns:MinBinValue>4.16016</ns:MinBinValue><ns:MaxBinValue>14.5391</ns:MaxBinValue><ns:MaxOutlierValue>14.5391</ns:MaxOutlierValue><ns:MetricDescription>Baseline Level: Channel G</ns:MetricDescription></BaselineLevelDist><BaselineLevelDist Channel="T"><ns:SampleSize>11</ns:SampleSize><ns:SampleMean>7.9201</ns:SampleMean><ns:SampleMed>6.58984</ns:SampleMed><ns:SampleMode>5.71699</ns:SampleMode><ns:SampleStd>2.98976</ns:SampleStd><ns:Sample95thPct>14.5391</ns:Sample95thPct><ns:NumBins>30</ns:NumBins><ns:BinCounts><ns:BinCount>1</ns:BinCount><ns:BinCount>0</ns:BinCount><ns:BinCount>0</ns:BinCount><ns:BinCount>1</ns:BinCount><ns:BinCount>2</ns:BinCount><ns:BinCount>1</ns:BinCount><ns:BinCount>0</ns:BinCount><ns:BinCount>1</ns:BinCount><ns:BinCount>0</ns:BinCount><ns:BinCount>0</ns:BinCount><ns:BinCount>0</ns:BinCount><ns:BinCount>1</ns:BinCount><ns:BinCount>0</ns:BinCount><ns:BinCount>0</ns:BinCount><ns:BinCount>0</ns:BinCount><ns:BinCount>0</ns:BinCount><ns:BinCount>0</ns:BinCount><ns:BinCount>2</ns:BinCount><ns:BinCount>1</ns:BinCount><ns:BinCount>0</ns:BinCount><ns:BinCount>0</ns:BinCount><ns:BinCount>0</ns:BinCount><ns:BinCount>0</ns:BinCount><ns:BinCount>0</ns:BinCount><ns:BinCount>0</ns:BinCount><ns:BinCount>0</ns:BinCount><ns:BinCount>0</ns:BinCount><ns:BinCount>0</ns:BinCount><ns:BinCount>0</ns:BinCount><ns:BinCount>0</ns:BinCount></ns:BinCounts><ns:BinWidth>0.345964</ns:BinWidth><ns:MinOutlierValue>4.16016</ns:MinOutlierValue><ns:MinBinValue>4.16016</ns:MinBinValue><ns:MaxBinValue>14.5391</ns:MaxBinValue><ns:MaxOutlierValue>14.5391</ns:MaxOutlierValue><ns:MetricDescription>Baseline Level: Channel T</ns:MetricDescription></BaselineLevelDist><BaselineStdDist Channel="A"><ns:SampleSize>11</ns:SampleSize><ns:SampleMean>2.45694</ns:SampleMean><ns:SampleMed>2.29297</ns:SampleMed><ns:SampleMode>1.99285</ns:SampleMode><ns:SampleStd>0.567087</ns:SampleStd><ns:Sample95thPct>3.92773</ns:Sample95thPct><ns:NumBins>30</ns:NumBins><ns:BinCounts><ns:BinCount>1</ns:BinCount><ns:BinCount>0</ns:BinCount><ns:BinCount>0</ns:BinCount><ns:BinCount>2</ns:BinCount><ns:BinCount>1</ns:BinCount><ns:BinCount>0</ns:BinCount><ns:BinCount>0</ns:BinCount><ns:BinCount>2</ns:BinCount><ns:BinCount>0</ns:BinCount><ns:BinCount>0</ns:BinCount><ns:BinCount>0</ns:BinCount><ns:BinCount>1</ns:BinCount><ns:BinCount>2</ns:BinCount><ns:BinCount>0</ns:BinCount><ns:BinCount>1</ns:BinCount><ns:BinCount>0</ns:BinCount><ns:BinCount>0</ns:BinCount><ns:BinCount>0</ns:BinCount><ns:BinCount>0</ns:BinCount><ns:BinCount>0</ns:BinCount><ns:BinCount>0</ns:BinCount><ns:BinCount>0</ns:BinCount><ns:BinCount>0</ns:BinCount><ns:BinCount>0</ns:BinCount><ns:BinCount>0</ns:BinCount><ns:BinCount>0</ns:BinCount><ns:BinCount>0</ns:BinCount><ns:BinCount>0</ns:BinCount><ns:BinCount>0</ns:BinCount><ns:BinCount>0</ns:BinCount></ns:BinCounts><ns:BinWidth>0.0730143</ns:BinWidth><ns:MinOutlierValue>1.7373</ns:MinOutlierValue><ns:MinBinValue>1.7373</ns:MinBinValue><ns:MaxBinValue>3.92773</ns:MaxBinValue><ns:MaxOutlierValue>3.92773</ns:MaxOutlierValue><ns:MetricDescription>Baseline Std: Channel A</ns:MetricDescription></BaselineStdDist><BaselineStdDist Channel="C"><ns:SampleSize>11</ns:SampleSize><ns:SampleMean>2.45694</ns:SampleMean><ns:SampleMed>2.29297</ns:SampleMed><ns:SampleMode>1.99285</ns:SampleMode><ns:SampleStd>0.567087</ns:SampleStd><ns:Sample95thPct>3.92773</ns:Sample95thPct><ns:NumBins>30</ns:NumBins><ns:BinCounts><ns:BinCount>1</ns:BinCount><ns:BinCount>0</ns:BinCount><ns:BinCount>0</ns:BinCount><ns:BinCount>2</ns:BinCount><ns:BinCount>1</ns:BinCount><ns:BinCount>0</ns:BinCount><ns:BinCount>0</ns:BinCount><ns:BinCount>2</ns:BinCount><ns:BinCount>0</ns:BinCount><ns:BinCount>0</ns:BinCount><ns:BinCount>0</ns:BinCount><ns:BinCount>1</ns:BinCount><ns:BinCount>2</ns:BinCount><ns:BinCount>0</ns:BinCount><ns:BinCount>1</ns:BinCount><ns:BinCount>0</ns:BinCount><ns:BinCount>0</ns:BinCount><ns:BinCount>0</ns:BinCount><ns:BinCount>0</ns:BinCount><ns:BinCount>0</ns:BinCount><ns:BinCount>0</ns:BinCount><ns:BinCount>0</ns:BinCount><ns:BinCount>0</ns:BinCount><ns:BinCount>0</ns:BinCount><ns:BinCount>0</ns:BinCount><ns:BinCount>0</ns:BinCount><ns:BinCount>0</ns:BinCount><ns:BinCount>0</ns:BinCount><ns:BinCount>0</ns:BinCount><ns:BinCount>0</ns:BinCount></ns:BinCounts><ns:BinWidth>0.0730143</ns:BinWidth><ns:MinOutlierValue>1.7373</ns:MinOutlierValue><ns:MinBinValue>1.7373</ns:MinBinValue><ns:MaxBinValue>3.92773</ns:MaxBinValue><ns:MaxOutlierValue>3.92773</ns:MaxOutlierValue><ns:MetricDescription>Baseline Std: Channel C</ns:MetricDescription></BaselineStdDist><BaselineStdDist Channel="G"><ns:SampleSize>11</ns:SampleSize><ns:SampleMean>2.45694</ns:SampleMean><ns:SampleMed>2.29297</ns:SampleMed><ns:SampleMode>1.99285</ns:SampleMode><ns:SampleStd>0.567087</ns:SampleStd><ns:Sample95thPct>3.92773</ns:Sample95thPct><ns:NumBins>30</ns:NumBins><ns:BinCounts><ns:BinCount>1</ns:BinCount><ns:BinCount>0</ns:BinCount><ns:BinCount>0</ns:BinCount><ns:BinCount>2</ns:BinCount><ns:BinCount>1</ns:BinCount><ns:BinCount>0</ns:BinCount><ns:BinCount>0</ns:BinCount><ns:BinCount>2</ns:BinCount><ns:BinCount>0</ns:BinCount><ns:BinCount>0</ns:BinCount><ns:BinCount>0</ns:BinCount><ns:BinCount>1</ns:BinCount><ns:BinCount>2</ns:BinCount><ns:BinCount>0</ns:BinCount><ns:BinCount>1</ns:BinCount><ns:BinCount>0</ns:BinCount><ns:BinCount>0</ns:BinCount><ns:BinCount>0</ns:BinCount><ns:BinCount>0</ns:BinCount><ns:BinCount>0</ns:BinCount><ns:BinCount>0</ns:BinCount><ns:BinCount>0</ns:BinCount><ns:BinCount>0</ns:BinCount><ns:BinCount>0</ns:BinCount><ns:BinCount>0</ns:BinCount><ns:BinCount>0</ns:BinCount><ns:BinCount>0</ns:BinCount><ns:BinCount>0</ns:BinCount><ns:BinCount>0</ns:BinCount><ns:BinCount>0</ns:BinCount></ns:BinCounts><ns:BinWidth>0.0730143</ns:BinWidth><ns:MinOutlierValue>1.7373</ns:MinOutlierValue><ns:MinBinValue>1.7373</ns:MinBinValue><ns:MaxBinValue>3.92773</ns:MaxBinValue><ns:MaxOutlierValue>3.92773</ns:MaxOutlierValue><ns:MetricDescription>Baseline Std: Channel G</ns:MetricDescription></BaselineStdDist><BaselineStdDist Channel="T"><ns:SampleSize>11</ns:SampleSize><ns:SampleMean>2.45694</ns:SampleMean><ns:SampleMed>2.29297</ns:SampleMed><ns:SampleMode>1.99285</ns:SampleMode><ns:SampleStd>0.567087</ns:SampleStd><ns:Sample95thPct>3.92773</ns:Sample95thPct><ns:NumBins>30</ns:NumBins><ns:BinCounts><ns:BinCount>1</ns:BinCount><ns:BinCount>0</ns:BinCount><ns:BinCount>0</ns:BinCount><ns:BinCount>2</ns:BinCount><ns:BinCount>1</ns:BinCount><ns:BinCount>0</ns:BinCount><ns:BinCount>0</ns:BinCount><ns:BinCount>2</ns:BinCount><ns:BinCount>0</ns:BinCount><ns:BinCount>0</ns:BinCount><ns:BinCount>0</ns:BinCount><ns:BinCount>1</ns:BinCount><ns:BinCount>2</ns:BinCount><ns:BinCount>0</ns:BinCount><ns:BinCount>1</ns:BinCount><ns:BinCount>0</ns:BinCount><ns:BinCount>0</ns:BinCount><ns:BinCount>0</ns:BinCount><ns:BinCount>0</ns:BinCount><ns:BinCount>0</ns:BinCount><ns:BinCount>0</ns:BinCount><ns:BinCount>0</ns:BinCount><ns:BinCount>0</ns:BinCount><ns:BinCount>0</ns:BinCount><ns:BinCount>0</ns:BinCount><ns:BinCount>0</ns:BinCount><ns:BinCount>0</ns:BinCount><ns:BinCount>0</ns:BinCount><ns:BinCount>0</ns:BinCount><ns:BinCount>0</ns:BinCount></ns:BinCounts><ns:BinWidth>0.0730143</ns:BinWidth><ns:MinOutlierValue>1.7373</ns:MinOutlierValue><ns:MinBinValue>1.7373</ns:MinBinValue><ns:MaxBinValue>3.92773</ns:MaxBinValue><ns:MaxOutlierValue>3.92773</ns:MaxOutlierValue><ns:MetricDescription>Baseline Std: Channel T</ns:MetricDescription></BaselineStdDist><SnrDist Channel="A"><ns:SampleSize>11</ns:SampleSize><ns:SampleMean>12.4761</ns:SampleMean><ns:SampleMed>12.0182</ns:SampleMed><ns:SampleMode>11.4428</ns:SampleMode><ns:SampleStd>1.92623</ns:SampleStd><ns:Sample95thPct>18.1878</ns:Sample95thPct><ns:NumBins>30</ns:NumBins><ns:BinCounts><ns:BinCount>1</ns:BinCount><ns:BinCount>1</ns:BinCount><ns:BinCount>2</ns:BinCount><ns:BinCount>1</ns:BinCount><ns:BinCount>2</ns:BinCount><ns:BinCount>0</ns:BinCount><ns:BinCount>2</ns:BinCount><ns:BinCount>0</ns:BinCount><ns:BinCount>0</ns:BinCount><ns:BinCount>0</ns:BinCount><ns:BinCount>1</ns:BinCount><ns:BinCount>0</ns:BinCount><ns:BinCount>0</ns:BinCount><ns:BinCount>0</ns:BinCount><ns:BinCount>0</ns:BinCount><ns:BinCount>0</ns:BinCount><ns:BinCount>0</ns:BinCount><ns:BinCount>0</ns:BinCount><ns:BinCount>0</ns:BinCount><ns:BinCount>0</ns:BinCount><ns:BinCount>0</ns:BinCount><ns:BinCount>0</ns:BinCount><ns:BinCount>0</ns:BinCount><ns:BinCount>0</ns:BinCount><ns:BinCount>0</ns:BinCount><ns:BinCount>0</ns:BinCount><ns:BinCount>0</ns:BinCount><ns:BinCount>0</ns:BinCount><ns:BinCount>0</ns:BinCount><ns:BinCount>0</ns:BinCount></ns:BinCounts><ns:BinWidth>0.245275</ns:BinWidth><ns:MinOutlierValue>10.8296</ns:MinOutlierValue><ns:MinBinValue>10.8296</ns:MinBinValue><ns:MaxBinValue>18.1878</ns:MaxBinValue><ns:MaxOutlierValue>18.1878</ns:MaxOutlierValue><ns:MetricDescription>Signal to Noise Ratio: Channel A</ns:MetricDescription></SnrDist><SnrDist Channel="C"><ns:SampleSize>11</ns:SampleSize><ns:SampleMean>16.7284</ns:SampleMean><ns:SampleMed>16.0413</ns:SampleMed><ns:SampleMode>16.1705</ns:SampleMode><ns:SampleStd>3.74558</ns:SampleStd><ns:Sample95thPct>26.3425</ns:Sample95thPct><ns:NumBins>30</ns:NumBins><ns:BinCounts><ns:BinCount>1</ns:BinCount><ns:BinCount>0</ns:BinCount><ns:BinCount>0</ns:BinCount><ns:BinCount>0</ns:BinCount><ns:BinCount>0</ns:BinCount><ns:BinCount>0</ns:BinCount><ns:BinCount>1</ns:BinCount><ns:BinCount>1</ns:BinCount><ns:BinCount>1</ns:BinCount><ns:BinCount>1</ns:BinCount><ns:BinCount>2</ns:BinCount><ns:BinCount>0</ns:BinCount><ns:BinCount>0</ns:BinCount><ns:BinCount>0</ns:BinCount><ns:BinCount>2</ns:BinCount><ns:BinCount>1</ns:BinCount><ns:BinCount>0</ns:BinCount><ns:BinCount>0</ns:BinCount><ns:BinCount>0</ns:BinCount><ns:BinCount>0</ns:BinCount><ns:BinCount>0</ns:BinCount><ns:BinCount>0</ns:BinCount><ns:BinCount>0</ns:BinCount><ns:BinCount>0</ns:BinCount><ns:BinCount>0</ns:BinCount><ns:BinCount>0</ns:BinCount><ns:BinCount>0</ns:BinCount><ns:BinCount>0</ns:BinCount><ns:BinCount>0</ns:BinCount><ns:BinCount>0</ns:BinCount></ns:BinCounts><ns:BinWidth>0.521645</ns:BinWidth><ns:MinOutlierValue>10.6932</ns:MinOutlierValue><ns:MinBinValue>10.6932</ns:MinBinValue><ns:MaxBinValue>26.3425</ns:MaxBinValue><ns:MaxOutlierValue>26.3425</ns:MaxOutlierValue><ns:MetricDescription>Signal to Noise Ratio: Channel C</ns:MetricDescription></SnrDist><SnrDist Channel="G"><ns:SampleSize>11</ns:SampleSize><ns:SampleMean>6.92833</ns:SampleMean><ns:SampleMed>6.48196</ns:SampleMed><ns:SampleMode>6.1792</ns:SampleMode><ns:SampleStd>0.984833</ns:SampleStd><ns:Sample95thPct>8.91873</ns:Sample95thPct><ns:NumBins>30</ns:NumBins><ns:BinCounts><ns:BinCount>1</ns:BinCount><ns:BinCount>2</ns:BinCount><ns:BinCount>0</ns:BinCount><ns:BinCount>2</ns:BinCount><ns:BinCount>1</ns:BinCount><ns:BinCount>2</ns:BinCount><ns:BinCount>0</ns:BinCount><ns:BinCount>0</ns:BinCount><ns:BinCount>0</ns:BinCount><ns:BinCount>0</ns:BinCount><ns:BinCount>0</ns:BinCount><ns:BinCount>0</ns:BinCount><ns:BinCount>0</ns:BinCount><ns:BinCount>0</ns:BinCount><ns:BinCount>0</ns:BinCount><ns:BinCount>0</ns:BinCount><ns:BinCount>0</ns:BinCount><ns:BinCount>0</ns:BinCount><ns:BinCount>0</ns:BinCount><ns:BinCount>1</ns:BinCount><ns:BinCount>0</ns:BinCount><ns:BinCount>0</ns:BinCount><ns:BinCount>0</ns:BinCount><ns:BinCount>0</ns:BinCount><ns:BinCount>0</ns:BinCount><ns:BinCount>0</ns:BinCount><ns:BinCount>1</ns:BinCount><ns:BinCount>0</ns:BinCount><ns:BinCount>0</ns:BinCount><ns:BinCount>0</ns:BinCount></ns:BinCounts><ns:BinWidth>0.0961238</ns:BinWidth><ns:MinOutlierValue>6.03502</ns:MinOutlierValue><ns:MinBinValue>6.03502</ns:MinBinValue><ns:MaxBinValue>8.91873</ns:MaxBinValue><ns:MaxOutlierValue>8.91873</ns:MaxOutlierValue><ns:MetricDescription>Signal to Noise Ratio: Channel G</ns:MetricDescription></SnrDist><SnrDist Channel="T"><ns:SampleSize>11</ns:SampleSize><ns:SampleMean>9.41604</ns:SampleMean><ns:SampleMed>9.4447</ns:SampleMed><ns:SampleMode>9.43452</ns:SampleMode><ns:SampleStd>1.32999</ns:SampleStd><ns:Sample95thPct>11.6395</ns:Sample95thPct><ns:NumBins>30</ns:NumBins><ns:BinCounts><ns:BinCount>1</ns:BinCount><ns:BinCount>1</ns:BinCount><ns:BinCount>0</ns:BinCount><ns:BinCount>0</ns:BinCount><ns:BinCount>0</ns:BinCount><ns:BinCount>1</ns:BinCount><ns:BinCount>1</ns:BinCount><ns:BinCount>0</ns:BinCount><ns:BinCount>0</ns:BinCount><ns:BinCount>0</ns:BinCount><ns:BinCount>0</ns:BinCount><ns:BinCount>0</ns:BinCount><ns:BinCount>0</ns:BinCount><ns:BinCount>0</ns:BinCount><ns:BinCount>2</ns:BinCount><ns:BinCount>0</ns:BinCount><ns:BinCount>0</ns:BinCount><ns:BinCount>0</ns:BinCount><ns:BinCount>2</ns:BinCount><ns:BinCount>0</ns:BinCount><ns:BinCount>0</ns:BinCount><ns:BinCount>0</ns:BinCount><ns:BinCount>0</ns:BinCount><ns:BinCount>1</ns:BinCount><ns:BinCount>1</ns:BinCount><ns:BinCount>0</ns:BinCount><ns:BinCount>0</ns:BinCount><ns:BinCount>0</ns:BinCount><ns:BinCount>0</ns:BinCount><ns:BinCount>0</ns:BinCount></ns:BinCounts><ns:BinWidth>0.14226</ns:BinWidth><ns:MinOutlierValue>7.37176</ns:MinOutlierValue><ns:MinBinValue>7.37176</ns:MinBinValue><ns:MaxBinValue>11.6395</ns:MaxBinValue><ns:MaxOutlierValue>11.6395</ns:MaxOutlierValue><ns:MetricDescription>Signal to Noise Ratio: Channel T</ns:MetricDescription></SnrDist><HqRegionSnrDist Channel="A"><ns:SampleSize>11</ns:SampleSize><ns:SampleMean>12.4761</ns:SampleMean><ns:SampleMed>12.0182</ns:SampleMed><ns:SampleMode>11.4428</ns:SampleMode><ns:SampleStd>1.92623</ns:SampleStd><ns:Sample95thPct>18.1878</ns:Sample95thPct><ns:NumBins>30</ns:NumBins><ns:BinCounts><ns:BinCount>1</ns:BinCount><ns:BinCount>1</ns:BinCount><ns:BinCount>2</ns:BinCount><ns:BinCount>1</ns:BinCount><ns:BinCount>2</ns:BinCount><ns:BinCount>0</ns:BinCount><ns:BinCount>2</ns:BinCount><ns:BinCount>0</ns:BinCount><ns:BinCount>0</ns:BinCount><ns:BinCount>0</ns:BinCount><ns:BinCount>1</ns:BinCount><ns:BinCount>0</ns:BinCount><ns:BinCount>0</ns:BinCount><ns:BinCount>0</ns:BinCount><ns:BinCount>0</ns:BinCount><ns:BinCount>0</ns:BinCount><ns:BinCount>0</ns:BinCount><ns:BinCount>0</ns:BinCount><ns:BinCount>0</ns:BinCount><ns:BinCount>0</ns:BinCount><ns:BinCount>0</ns:BinCount><ns:BinCount>0</ns:BinCount><ns:BinCount>0</ns:BinCount><ns:BinCount>0</ns:BinCount><ns:BinCount>0</ns:BinCount><ns:BinCount>0</ns:BinCount><ns:BinCount>0</ns:BinCount><ns:BinCount>0</ns:BinCount><ns:BinCount>0</ns:BinCount><ns:BinCount>0</ns:BinCount></ns:BinCounts><ns:BinWidth>0.245275</ns:BinWidth><ns:MinOutlierValue>10.8296</ns:MinOutlierValue><ns:MinBinValue>10.8296</ns:MinBinValue><ns:MaxBinValue>18.1878</ns:MaxBinValue><ns:MaxOutlierValue>18.1878</ns:MaxOutlierValue><ns:MetricDescription>HQ Region Signal to Noise Ratio: Channel A</ns:MetricDescription></HqRegionSnrDist><HqRegionSnrDist Channel="C"><ns:SampleSize>11</ns:SampleSize><ns:SampleMean>16.7284</ns:SampleMean><ns:SampleMed>16.0413</ns:SampleMed><ns:SampleMode>16.1705</ns:SampleMode><ns:SampleStd>3.74558</ns:SampleStd><ns:Sample95thPct>26.3425</ns:Sample95thPct><ns:NumBins>30</ns:NumBins><ns:BinCounts><ns:BinCount>1</ns:BinCount><ns:BinCount>0</ns:BinCount><ns:BinCount>0</ns:BinCount><ns:BinCount>0</ns:BinCount><ns:BinCount>0</ns:BinCount><ns:BinCount>0</ns:BinCount><ns:BinCount>1</ns:BinCount><ns:BinCount>1</ns:BinCount><ns:BinCount>1</ns:BinCount><ns:BinCount>1</ns:BinCount><ns:BinCount>2</ns:BinCount><ns:BinCount>0</ns:BinCount><ns:BinCount>0</ns:BinCount><ns:BinCount>0</ns:BinCount><ns:BinCount>2</ns:BinCount><ns:BinCount>1</ns:BinCount><ns:BinCount>0</ns:BinCount><ns:BinCount>0</ns:BinCount><ns:BinCount>0</ns:BinCount><ns:BinCount>0</ns:BinCount><ns:BinCount>0</ns:BinCount><ns:BinCount>0</ns:BinCount><ns:BinCount>0</ns:BinCount><ns:BinCount>0</ns:BinCount><ns:BinCount>0</ns:BinCount><ns:BinCount>0</ns:BinCount><ns:BinCount>0</ns:BinCount><ns:BinCount>0</ns:BinCount><ns:BinCount>0</ns:BinCount><ns:BinCount>0</ns:BinCount></ns:BinCounts><ns:BinWidth>0.521645</ns:BinWidth><ns:MinOutlierValue>10.6932</ns:MinOutlierValue><ns:MinBinValue>10.6932</ns:MinBinValue><ns:MaxBinValue>26.3425</ns:MaxBinValue><ns:MaxOutlierValue>26.3425</ns:MaxOutlierValue><ns:MetricDescription>HQ Region Signal to Noise Ratio: Channel C</ns:MetricDescription></HqRegionSnrDist><HqRegionSnrDist Channel="G"><ns:SampleSize>11</ns:SampleSize><ns:SampleMean>6.92833</ns:SampleMean><ns:SampleMed>6.48196</ns:SampleMed><ns:SampleMode>6.1792</ns:SampleMode><ns:SampleStd>0.984833</ns:SampleStd><ns:Sample95thPct>8.91873</ns:Sample95thPct><ns:NumBins>30</ns:NumBins><ns:BinCounts><ns:BinCount>1</ns:BinCount><ns:BinCount>2</ns:BinCount><ns:BinCount>0</ns:BinCount><ns:BinCount>2</ns:BinCount><ns:BinCount>1</ns:BinCount><ns:BinCount>2</ns:BinCount><ns:BinCount>0</ns:BinCount><ns:BinCount>0</ns:BinCount><ns:BinCount>0</ns:BinCount><ns:BinCount>0</ns:BinCount><ns:BinCount>0</ns:BinCount><ns:BinCount>0</ns:BinCount><ns:BinCount>0</ns:BinCount><ns:BinCount>0</ns:BinCount><ns:BinCount>0</ns:BinCount><ns:BinCount>0</ns:BinCount><ns:BinCount>0</ns:BinCount><ns:BinCount>0</ns:BinCount><ns:BinCount>0</ns:BinCount><ns:BinCount>1</ns:BinCount><ns:BinCount>0</ns:BinCount><ns:BinCount>0</ns:BinCount><ns:BinCount>0</ns:BinCount><ns:BinCount>0</ns:BinCount><ns:BinCount>0</ns:BinCount><ns:BinCount>0</ns:BinCount><ns:BinCount>1</ns:BinCount><ns:BinCount>0</ns:BinCount><ns:BinCount>0</ns:BinCount><ns:BinCount>0</ns:BinCount></ns:BinCounts><ns:BinWidth>0.0961238</ns:BinWidth><ns:MinOutlierValue>6.03502</ns:MinOutlierValue><ns:MinBinValue>6.03502</ns:MinBinValue><ns:MaxBinValue>8.91873</ns:MaxBinValue><ns:MaxOutlierValue>8.91873</ns:MaxOutlierValue><ns:MetricDescription>HQ Region Signal to Noise Ratio: Channel G</ns:MetricDescription></HqRegionSnrDist><HqRegionSnrDist Channel="T"><ns:SampleSize>11</ns:SampleSize><ns:SampleMean>9.41604</ns:SampleMean><ns:SampleMed>9.4447</ns:SampleMed><ns:SampleMode>9.43452</ns:SampleMode><ns:SampleStd>1.32999</ns:SampleStd><ns:Sample95thPct>11.6395</ns:Sample95thPct><ns:NumBins>30</ns:NumBins><ns:BinCounts><ns:BinCount>1</ns:BinCount><ns:BinCount>1</ns:BinCount><ns:BinCount>0</ns:BinCount><ns:BinCount>0</ns:BinCount><ns:BinCount>0</ns:BinCount><ns:BinCount>1</ns:BinCount><ns:BinCount>1</ns:BinCount><ns:BinCount>0</ns:BinCount><ns:BinCount>0</ns:BinCount><ns:BinCount>0</ns:BinCount><ns:BinCount>0</ns:BinCount><ns:BinCount>0</ns:BinCount><ns:BinCount>0</ns:BinCount><ns:BinCount>0</ns:BinCount><ns:BinCount>2</ns:BinCount><ns:BinCount>0</ns:BinCount><ns:BinCount>0</ns:BinCount><ns:BinCount>0</ns:BinCount><ns:BinCount>2</ns:BinCount><ns:BinCount>0</ns:BinCount><ns:BinCount>0</ns:BinCount><ns:BinCount>0</ns:BinCount><ns:BinCount>0</ns:BinCount><ns:BinCount>1</ns:BinCount><ns:BinCount>1</ns:BinCount><ns:BinCount>0</ns:BinCount><ns:BinCount>0</ns:BinCount><ns:BinCount>0</ns:BinCount><ns:BinCount>0</ns:BinCount><ns:BinCount>0</ns:BinCount></ns:BinCounts><ns:BinWidth>0.14226</ns:BinWidth><ns:MinOutlierValue>7.37176</ns:MinOutlierValue><ns:MinBinValue>7.37176</ns:MinBinValue><ns:MaxBinValue>11.6395</ns:MaxBinValue><ns:MaxOutlierValue>11.6395</ns:MaxOutlierValue><ns:MetricDescription>HQ Region Signal to Noise Ratio: Channel T</ns:MetricDescription></HqRegionSnrDist><HqBasPkMidDist Channel="A"><ns:SampleSize>11</ns:SampleSize><ns:SampleMean>30.6448</ns:SampleMean><ns:SampleMed>30.4062</ns:SampleMed><ns:SampleMode>31.0917</ns:SampleMode><ns:SampleStd>8.53107</ns:SampleStd><ns:Sample95thPct>51.4375</ns:Sample95thPct><ns:NumBins>30</ns:NumBins><ns:BinCounts><ns:BinCount>1</ns:BinCount><ns:BinCount>1</ns:BinCount><ns:BinCount>1</ns:BinCount><ns:BinCount>1</ns:BinCount><ns:BinCount>1</ns:BinCount><ns:BinCount>0</ns:BinCount><ns:BinCount>0</ns:BinCount><ns:BinCount>0</ns:BinCount><ns:BinCount>1</ns:BinCount><ns:BinCount>3</ns:BinCount><ns:BinCount>0</ns:BinCount><ns:BinCount>0</ns:BinCount><ns:BinCount>0</ns:BinCount><ns:BinCount>0</ns:BinCount><ns:BinCount>0</ns:BinCount><ns:BinCount>0</ns:BinCount><ns:BinCount>0</ns:BinCount><ns:BinCount>0</ns:BinCount><ns:BinCount>0</ns:BinCount><ns:BinCount>0</ns:BinCount><ns:BinCount>0</ns:BinCount><ns:BinCount>1</ns:BinCount><ns:BinCount>0</ns:BinCount><ns:BinCount>0</ns:BinCount><ns:BinCount>0</ns:BinCount><ns:BinCount>0</ns:BinCount><ns:BinCount>0</ns:BinCount><ns:BinCount>0</ns:BinCount><ns:BinCount>0</ns:BinCount><ns:BinCount>0</ns:BinCount></ns:BinCounts><ns:BinWidth>0.992479</ns:BinWidth><ns:MinOutlierValue>21.6631</ns:MinOutlierValue><ns:MinBinValue>21.6631</ns:MinBinValue><ns:MaxBinValue>51.4375</ns:MaxBinValue><ns:MaxOutlierValue>51.4375</ns:MaxOutlierValue><ns:MetricDescription>HQ Region PkMid: Channel A</ns:MetricDescription></HqBasPkMidDist><HqBasPkMidDist Channel="C"><ns:SampleSize>11</ns:SampleSize><ns:SampleMean>40.5292</ns:SampleMean><ns:SampleMed>36.9062</ns:SampleMed><ns:SampleMode>30.9414</ns:SampleMode><ns:SampleStd>11.7961</ns:SampleStd><ns:Sample95thPct>74.5</ns:Sample95thPct><ns:NumBins>30</ns:NumBins><ns:BinCounts><ns:BinCount>2</ns:BinCount><ns:BinCount>1</ns:BinCount><ns:BinCount>1</ns:BinCount><ns:BinCount>0</ns:BinCount><ns:BinCount>2</ns:BinCount><ns:BinCount>0</ns:BinCount><ns:BinCount>1</ns:BinCount><ns:BinCount>1</ns:BinCount><ns:BinCount>1</ns:BinCount><ns:BinCount>0</ns:BinCount><ns:BinCount>0</ns:BinCount><ns:BinCount>1</ns:BinCount><ns:BinCount>0</ns:BinCount><ns:BinCount>0</ns:BinCount><ns:BinCount>0</ns:BinCount><ns:BinCount>0</ns:BinCount><ns:BinCount>0</ns:BinCount><ns:BinCount>0</ns:BinCount><ns:BinCount>0</ns:BinCount><ns:BinCount>0</ns:BinCount><ns:BinCount>0</ns:BinCount><ns:BinCount>0</ns:BinCount><ns:BinCount>0</ns:BinCount><ns:BinCount>0</ns:BinCount><ns:BinCount>0</ns:BinCount><ns:BinCount>0</ns:BinCount><ns:BinCount>0</ns:BinCount><ns:BinCount>0</ns:BinCount><ns:BinCount>0</ns:BinCount><ns:BinCount>0</ns:BinCount></ns:BinCounts><ns:BinWidth>1.47656</ns:BinWidth><ns:MinOutlierValue>30.2031</ns:MinOutlierValue><ns:MinBinValue>30.2031</ns:MinBinValue><ns:MaxBinValue>74.5</ns:MaxBinValue><ns:MaxOutlierValue>74.5</ns:MaxOutlierValue><ns:MetricDescription>HQ Region PkMid: Channel C</ns:MetricDescription></HqBasPkMidDist><HqBasPkMidDist Channel="G"><ns:SampleSize>11</ns:SampleSize><ns:SampleMean>17.0223</ns:SampleMean><ns:SampleMed>17.2683</ns:SampleMed><ns:SampleMode>11.3268</ns:SampleMode><ns:SampleStd>4.31868</ns:SampleStd><ns:Sample95thPct>24.4088</ns:Sample95thPct><ns:NumBins>30</ns:NumBins><ns:BinCounts><ns:BinCount>1</ns:BinCount><ns:BinCount>0</ns:BinCount><ns:BinCount>1</ns:BinCount><ns:BinCount>1</ns:BinCount><ns:BinCount>0</ns:BinCount><ns:BinCount>1</ns:BinCount><ns:BinCount>0</ns:BinCount><ns:BinCount>0</ns:BinCount><ns:BinCount>1</ns:BinCount><ns:BinCount>0</ns:BinCount><ns:BinCount>0</ns:BinCount><ns:BinCount>0</ns:BinCount><ns:BinCount>0</ns:BinCount><ns:BinCount>1</ns:BinCount><ns:BinCount>0</ns:BinCount><ns:BinCount>1</ns:BinCount><ns:BinCount>0</ns:BinCount><ns:BinCount>0</ns:BinCount><ns:BinCount>0</ns:BinCount><ns:BinCount>0</ns:BinCount><ns:BinCount>0</ns:BinCount><ns:BinCount>1</ns:BinCount><ns:BinCount>1</ns:BinCount><ns:BinCount>0</ns:BinCount><ns:BinCount>1</ns:BinCount><ns:BinCount>0</ns:BinCount><ns:BinCount>0</ns:BinCount><ns:BinCount>0</ns:BinCount><ns:BinCount>0</ns:BinCount><ns:BinCount>0</ns:BinCount></ns:BinCounts><ns:BinWidth>0.443458</ns:BinWidth><ns:MinOutlierValue>11.1051</ns:MinOutlierValue><ns:MinBinValue>11.1051</ns:MinBinValue><ns:MaxBinValue>24.4088</ns:MaxBinValue><ns:MaxOutlierValue>24.4088</ns:MaxOutlierValue><ns:MetricDescription>HQ Region PkMid: Channel G</ns:MetricDescription></HqBasPkMidDist><HqBasPkMidDist Channel="T"><ns:SampleSize>11</ns:SampleSize><ns:SampleMean>22.9752</ns:SampleMean><ns:SampleMed>21.6564</ns:SampleMed><ns:SampleMode>19.7441</ns:SampleMode><ns:SampleStd>5.35408</ns:SampleStd><ns:Sample95thPct>32.9181</ns:Sample95thPct><ns:NumBins>30</ns:NumBins><ns:BinCounts><ns:BinCount>1</ns:BinCount><ns:BinCount>0</ns:BinCount><ns:BinCount>0</ns:BinCount><ns:BinCount>0</ns:BinCount><ns:BinCount>0</ns:BinCount><ns:BinCount>0</ns:BinCount><ns:BinCount>1</ns:BinCount><ns:BinCount>0</ns:BinCount><ns:BinCount>3</ns:BinCount><ns:BinCount>0</ns:BinCount><ns:BinCount>0</ns:BinCount><ns:BinCount>2</ns:BinCount><ns:BinCount>0</ns:BinCount><ns:BinCount>0</ns:BinCount><ns:BinCount>0</ns:BinCount><ns:BinCount>0</ns:BinCount><ns:BinCount>0</ns:BinCount><ns:BinCount>0</ns:BinCount><ns:BinCount>1</ns:BinCount><ns:BinCount>0</ns:BinCount><ns:BinCount>0</ns:BinCount><ns:BinCount>0</ns:BinCount><ns:BinCount>1</ns:BinCount><ns:BinCount>0</ns:BinCount><ns:BinCount>0</ns:BinCount><ns:BinCount>1</ns:BinCount><ns:BinCount>0</ns:BinCount><ns:BinCount>0</ns:BinCount><ns:BinCount>0</ns:BinCount><ns:BinCount>0</ns:BinCount></ns:BinCounts><ns:BinWidth>0.612745</ns:BinWidth><ns:MinOutlierValue>14.5357</ns:MinOutlierValue><ns:MinBinValue>14.5357</ns:MinBinValue><ns:MaxBinValue>32.9181</ns:MaxBinValue><ns:MaxOutlierValue>32.9181</ns:MaxOutlierValue><ns:MetricDescription>HQ Region PkMid: Channel T</ns:MetricDescription></HqBasPkMidDist><PausinessDist><ns:SampleSize>11</ns:SampleSize><ns:SampleMean>0</ns:SampleMean><ns:SampleMed>0</ns:SampleMed><ns:SampleMode>0</ns:SampleMode><ns:SampleStd>0</ns:SampleStd><ns:Sample95thPct>0</ns:Sample95thPct><ns:NumBins>30</ns:NumBins><ns:BinCounts><ns:BinCount>0</ns:BinCount><ns:BinCount>0</ns:BinCount><ns:BinCount>0</ns:BinCount><ns:BinCount>0</ns:BinCount><ns:BinCount>0</ns:BinCount><ns:BinCount>0</ns:BinCount><ns:BinCount>0</ns:BinCount><ns:BinCount>0</ns:BinCount><ns:BinCount>0</ns:BinCount><ns:BinCount>0</ns:BinCount><ns:BinCount>0</ns:BinCount><ns:BinCount>0</ns:BinCount><ns:BinCount>0</ns:BinCount><ns:BinCount>0</ns:BinCount><ns:BinCount>0</ns:BinCount><ns:BinCount>0</ns:BinCount><ns:BinCount>0</ns:BinCount><ns:BinCount>0</ns:BinCount><ns:BinCount>0</ns:BinCount><ns:BinCount>0</ns:BinCount><ns:BinCount>0</ns:BinCount><ns:BinCount>0</ns:BinCount><ns:BinCount>0</ns:BinCount><ns:BinCount>0</ns:BinCount><ns:BinCount>0</ns:BinCount><ns:BinCount>0</ns:BinCount><ns:BinCount>0</ns:BinCount><ns:BinCount>0</ns:BinCount><ns:BinCount>0</ns:BinCount><ns:BinCount>0</ns:BinCount></ns:BinCounts><ns:BinWidth>0</ns:BinWidth><ns:MinOutlierValue>0</ns:MinOutlierValue><ns:MinBinValue>0</ns:MinBinValue><ns:MaxBinValue>0</ns:MaxBinValue><ns:MaxOutlierValue>0</ns:MaxOutlierValue><ns:MetricDescription>Pausiness</ns:MetricDescription></PausinessDist><AdapterDimerFraction>0</AdapterDimerFraction><ShortInsertFraction>0</ShortInsertFraction><IsReadsFraction>1.24603e-07</IsReadsFraction><ProdDist><ns:NumBins>4</ns:NumBins><ns:BinCounts><ns:BinCount>8014486</ns:BinCount><ns:BinCount>11</ns:BinCount><ns:BinCount>174</ns:BinCount><ns:BinCount>10801</ns:BinCount></ns:BinCounts><ns:MetricDescription>Productivity</ns:MetricDescription><ns:BinLabels><ns:BinLabel>Empty</ns:BinLabel><ns:BinLabel>Productive</ns:BinLabel><ns:BinLabel>Other</ns:BinLabel><ns:BinLabel>Undefined</ns:BinLabel></ns:BinLabels></ProdDist><LoadingDist><ns:NumBins>5</ns:NumBins><ns:BinCounts><ns:BinCount>8014497</ns:BinCount><ns:BinCount>0</ns:BinCount><ns:BinCount>0</ns:BinCount><ns:BinCount>174</ns:BinCount><ns:BinCount>10801</ns:BinCount></ns:BinCounts><ns:MetricDescription>Loading</ns:MetricDescription><ns:BinLabels><ns:BinLabel>Empty</ns:BinLabel><ns:BinLabel>Single</ns:BinLabel><ns:BinLabel>Multi</ns:BinLabel><ns:BinLabel>Indeterminate</ns:BinLabel><ns:BinLabel>Undefined</ns:BinLabel></ns:BinLabels></LoadingDist><ReadTypeDist><ns:NumBins>8</ns:NumBins><ns:BinCounts><ns:BinCount>8014497</ns:BinCount><ns:BinCount>0</ns:BinCount><ns:BinCount>0</ns:BinCount><ns:BinCount>0</ns:BinCount><ns:BinCount>0</ns:BinCount><ns:BinCount>0</ns:BinCount><ns:BinCount>174</ns:BinCount><ns:BinCount>10801</ns:BinCount></ns:BinCounts><ns:MetricDescription>ReadTypeDist</ns:MetricDescription><ns:BinLabels><ns:BinLabel>Empty</ns:BinLabel><ns:BinLabel>FullHqRead0</ns:BinLabel><ns:BinLabel>FullHqRead1</ns:BinLabel><ns:BinLabel>PartialHqRead0</ns:BinLabel><ns:BinLabel>PartialHqRead1</ns:BinLabel><ns:BinLabel>PartialHqRead2</ns:BinLabel><ns:BinLabel>Indeterminate</ns:BinLabel><ns:BinLabel>Undefined</ns:BinLabel></ns:BinLabels></ReadTypeDist><PulseRateDist><ns:SampleSize>11</ns:SampleSize><ns:SampleMean>0.53267</ns:SampleMean><ns:SampleMed>0.549316</ns:SampleMed><ns:SampleMode>0.318807</ns:SampleMode><ns:SampleStd>0.142197</ns:SampleStd><ns:Sample95thPct>0.762939</ns:Sample95thPct><ns:NumBins>30</ns:NumBins><ns:BinCounts><ns:BinCount>1</ns:BinCount><ns:BinCount>1</ns:BinCount><ns:BinCount>0</ns:BinCount><ns:BinCount>0</ns:BinCount><ns:BinCount>0</ns:BinCount><ns:BinCount>1</ns:BinCount><ns:BinCount>0</ns:BinCount><ns:BinCount>0</ns:BinCount><ns:BinCount>0</ns:BinCount><ns:BinCount>0</ns:BinCount><ns:BinCount>1</ns:BinCount><ns:BinCount>1</ns:BinCount><ns:BinCount>0</ns:BinCount><ns:BinCount>0</ns:BinCount><ns:BinCount>0</ns:BinCount><ns:BinCount>1</ns:BinCount><ns:BinCount>0</ns:BinCount><ns:BinCount>1</ns:BinCount><ns:BinCount>0</ns:BinCount><ns:BinCount>0</ns:BinCount><ns:BinCount>1</ns:BinCount><ns:BinCount>1</ns:BinCount><ns:BinCount>0</ns:BinCount><ns:BinCount>0</ns:BinCount><ns:BinCount>0</ns:BinCount><ns:BinCount>0</ns:BinCount><ns:BinCount>0</ns:BinCount><ns:BinCount>1</ns:BinCount><ns:BinCount>0</ns:BinCount><ns:BinCount>0</ns:BinCount></ns:BinCounts><ns:BinWidth>0.0150553</ns:BinWidth><ns:MinOutlierValue>0.311279</ns:MinOutlierValue><ns:MinBinValue>0.311279</ns:MinBinValue><ns:MaxBinValue>0.762939</ns:MaxBinValue><ns:MaxOutlierValue>0.762939</ns:MaxOutlierValue><ns:MetricDescription>Pulse Rate</ns:MetricDescription></PulseRateDist><PulseWidthDist><ns:SampleSize>11</ns:SampleSize><ns:SampleMean>0.0843426</ns:SampleMean><ns:SampleMed>0.0832943</ns:SampleMed><ns:SampleMode>0.0785871</ns:SampleMode><ns:SampleStd>0.0171065</ns:SampleStd><ns:Sample95thPct>0.116449</ns:Sample95thPct><ns:NumBins>30</ns:NumBins><ns:BinCounts><ns:BinCount>1</ns:BinCount><ns:BinCount>0</ns:BinCount><ns:BinCount>1</ns:BinCount><ns:BinCount>1</ns:BinCount><ns:BinCount>0</ns:BinCount><ns:BinCount>0</ns:BinCount><ns:BinCount>0</ns:BinCount><ns:BinCount>0</ns:BinCount><ns:BinCount>0</ns:BinCount><ns:BinCount>2</ns:BinCount><ns:BinCount>0</ns:BinCount><ns:BinCount>0</ns:BinCount><ns:BinCount>1</ns:BinCount><ns:BinCount>2</ns:BinCount><ns:BinCount>0</ns:BinCount><ns:BinCount>1</ns:BinCount><ns:BinCount>0</ns:BinCount><ns:BinCount>0</ns:BinCount><ns:BinCount>0</ns:BinCount><ns:BinCount>0</ns:BinCount><ns:BinCount>0</ns:BinCount><ns:BinCount>0</ns:BinCount><ns:BinCount>0</ns:BinCount><ns:BinCount>0</ns:BinCount><ns:BinCount>0</ns:BinCount><ns:BinCount>0</ns:BinCount><ns:BinCount>0</ns:BinCount><ns:BinCount>0</ns:BinCount><ns:BinCount>1</ns:BinCount><ns:BinCount>0</ns:BinCount></ns:BinCounts><ns:BinWidth>0.00184692</ns:BinWidth><ns:MinOutlierValue>0.0610414</ns:MinOutlierValue><ns:MinBinValue>0.0610414</ns:MinBinValue><ns:MaxBinValue>0.116449</ns:MaxBinValue><ns:MaxOutlierValue>0.116449</ns:MaxOutlierValue><ns:MetricDescription>Pulse Width</ns:MetricDescription></PulseWidthDist><BaseRateDist><ns:SampleSize>11</ns:SampleSize><ns:SampleMean>0.523515</ns:SampleMean><ns:SampleMed>0.540161</ns:SampleMed><ns:SampleMode>0.318553</ns:SampleMode><ns:SampleStd>0.137691</ns:SampleStd><ns:Sample95thPct>0.747681</ns:Sample95thPct><ns:NumBins>30</ns:NumBins><ns:BinCounts><ns:BinCount>1</ns:BinCount><ns:BinCount>1</ns:BinCount><ns:BinCount>0</ns:BinCount><ns:BinCount>0</ns:BinCount><ns:BinCount>0</ns:BinCount><ns:BinCount>1</ns:BinCount><ns:BinCount>0</ns:BinCount><ns:BinCount>0</ns:BinCount><ns:BinCount>0</ns:BinCount><ns:BinCount>0</ns:BinCount><ns:BinCount>1</ns:BinCount><ns:BinCount>1</ns:BinCount><ns:BinCount>0</ns:BinCount><ns:BinCount>0</ns:BinCount><ns:BinCount>0</ns:BinCount><ns:BinCount>1</ns:BinCount><ns:BinCount>0</ns:BinCount><ns:BinCount>1</ns:BinCount><ns:BinCount>0</ns:BinCount><ns:BinCount>1</ns:BinCount><ns:BinCount>0</ns:BinCount><ns:BinCount>1</ns:BinCount><ns:BinCount>0</ns:BinCount><ns:BinCount>0</ns:BinCount><ns:BinCount>0</ns:BinCount><ns:BinCount>0</ns:BinCount><ns:BinCount>0</ns:BinCount><ns:BinCount>1</ns:BinCount><ns:BinCount>0</ns:BinCount><ns:BinCount>0</ns:BinCount></ns:BinCounts><ns:BinWidth>0.0145467</ns:BinWidth><ns:MinOutlierValue>0.311279</ns:MinOutlierValue><ns:MinBinValue>0.311279</ns:MinBinValue><ns:MaxBinValue>0.747681</ns:MaxBinValue><ns:MaxOutlierValue>0.747681</ns:MaxOutlierValue><ns:MetricDescription>Base Rate</ns:MetricDescription></BaseRateDist><BaseWidthDist><ns:SampleSize>11</ns:SampleSize><ns:SampleMean>0.0848653</ns:SampleMean><ns:SampleMed>0.0837749</ns:SampleMed><ns:SampleMode>0.0795516</ns:SampleMode><ns:SampleStd>0.0169878</ns:SampleStd><ns:Sample95thPct>0.116721</ns:Sample95thPct><ns:NumBins>30</ns:NumBins><ns:BinCounts><ns:BinCount>1</ns:BinCount><ns:BinCount>0</ns:BinCount><ns:BinCount>1</ns:BinCount><ns:BinCount>1</ns:BinCount><ns:BinCount>0</ns:BinCount><ns:BinCount>0</ns:BinCount><ns:BinCount>0</ns:BinCount><ns:BinCount>0</ns:BinCount><ns:BinCount>0</ns:BinCount><ns:BinCount>2</ns:BinCount><ns:BinCount>0</ns:BinCount><ns:BinCount>1</ns:BinCount><ns:BinCount>0</ns:BinCount><ns:BinCount>2</ns:BinCount><ns:BinCount>0</ns:BinCount><ns:BinCount>1</ns:BinCount><ns:BinCount>0</ns:BinCount><ns:BinCount>0</ns:BinCount><ns:BinCount>0</ns:BinCount><ns:BinCount>0</ns:BinCount><ns:BinCount>0</ns:BinCount><ns:BinCount>0</ns:BinCount><ns:BinCount>0</ns:BinCount><ns:BinCount>0</ns:BinCount><ns:BinCount>0</ns:BinCount><ns:BinCount>0</ns:BinCount><ns:BinCount>0</ns:BinCount><ns:BinCount>0</ns:BinCount><ns:BinCount>0</ns:BinCount><ns:BinCount>1</ns:BinCount></ns:BinCounts><ns:BinWidth>0.00181314</ns:BinWidth><ns:MinOutlierValue>0.0623268</ns:MinOutlierValue><ns:MinBinValue>0.0623268</ns:MinBinValue><ns:MaxBinValue>0.116721</ns:MaxBinValue><ns:MaxOutlierValue>0.116721</ns:MaxOutlierValue><ns:MetricDescription>Base Width</ns:MetricDescription></BaseWidthDist><BaseIpdDist><ns:SampleSize>11</ns:SampleSize><ns:SampleMean>0.217716</ns:SampleMean><ns:SampleMed>0.173123</ns:SampleMed><ns:SampleMode>0.161822</ns:SampleMode><ns:SampleStd>0.109778</ns:SampleStd><ns:Sample95thPct>0.461662</ns:Sample95thPct><ns:NumBins>30</ns:NumBins><ns:BinCounts><ns:BinCount>1</ns:BinCount><ns:BinCount>0</ns:BinCount><ns:BinCount>0</ns:BinCount><ns:BinCount>0</ns:BinCount><ns:BinCount>0</ns:BinCount><ns:BinCount>0</ns:BinCount><ns:BinCount>0</ns:BinCount><ns:BinCount>1</ns:BinCount><ns:BinCount>2</ns:BinCount><ns:BinCount>2</ns:BinCount><ns:BinCount>1</ns:BinCount><ns:BinCount>0</ns:BinCount><ns:BinCount>0</ns:BinCount><ns:BinCount>0</ns:BinCount><ns:BinCount>0</ns:BinCount><ns:BinCount>1</ns:BinCount><ns:BinCount>1</ns:BinCount><ns:BinCount>0</ns:BinCount><ns:BinCount>0</ns:BinCount><ns:BinCount>0</ns:BinCount><ns:BinCount>0</ns:BinCount><ns:BinCount>0</ns:BinCount><ns:BinCount>1</ns:BinCount><ns:BinCount>0</ns:BinCount><ns:BinCount>0</ns:BinCount><ns:BinCount>0</ns:BinCount><ns:BinCount>0</ns:BinCount><ns:BinCount>0</ns:BinCount><ns:BinCount>0</ns:BinCount><ns:BinCount>0</ns:BinCount></ns:BinCounts><ns:BinWidth>0.0139461</ns:BinWidth><ns:MinOutlierValue>0.0432809</ns:MinOutlierValue><ns:MinBinValue>0.0432809</ns:MinBinValue><ns:MaxBinValue>0.461662</ns:MaxBinValue><ns:MaxOutlierValue>0.461662</ns:MaxOutlierValue><ns:MetricDescription>Base Ipd</ns:MetricDescription></BaseIpdDist><LocalBaseRateDist><ns:SampleSize>11</ns:SampleSize><ns:SampleMean>3.78352</ns:SampleMean><ns:SampleMed>3.66083</ns:SampleMed><ns:SampleMode>4.19088</ns:SampleMode><ns:SampleStd>1.4415</ns:SampleStd><ns:Sample95thPct>7.48684</ns:Sample95thPct><ns:NumBins>30</ns:NumBins><ns:BinCounts><ns:BinCount>1</ns:BinCount><ns:BinCount>0</ns:BinCount><ns:BinCount>1</ns:BinCount><ns:BinCount>0</ns:BinCount><ns:BinCount>0</ns:BinCount><ns:BinCount>1</ns:BinCount><ns:BinCount>1</ns:BinCount><ns:BinCount>1</ns:BinCount><ns:BinCount>0</ns:BinCount><ns:BinCount>1</ns:BinCount><ns:BinCount>0</ns:BinCount><ns:BinCount>1</ns:BinCount><ns:BinCount>2</ns:BinCount><ns:BinCount>0</ns:BinCount><ns:BinCount>0</ns:BinCount><ns:BinCount>1</ns:BinCount><ns:BinCount>0</ns:BinCount><ns:BinCount>0</ns:BinCount><ns:BinCount>0</ns:BinCount><ns:BinCount>0</ns:BinCount><ns:BinCount>0</ns:BinCount><ns:BinCount>0</ns:BinCount><ns:BinCount>0</ns:BinCount><ns:BinCount>0</ns:BinCount><ns:BinCount>0</ns:BinCount><ns:BinCount>0</ns:BinCount><ns:BinCount>0</ns:BinCount><ns:BinCount>0</ns:BinCount><ns:BinCount>0</ns:BinCount><ns:BinCount>0</ns:BinCount></ns:BinCounts><ns:BinWidth>0.188341</ns:BinWidth><ns:MinOutlierValue>1.83662</ns:MinOutlierValue><ns:MinBinValue>1.83662</ns:MinBinValue><ns:MaxBinValue>7.48684</ns:MaxBinValue><ns:MaxOutlierValue>7.48684</ns:MaxOutlierValue><ns:MetricDescription>Local Base Rate</ns:MetricDescription></LocalBaseRateDist><NumUnfilteredBasecallsDist><ns:SampleSize>11</ns:SampleSize><ns:SampleMean>165.727</ns:SampleMean><ns:SampleMed>177</ns:SampleMed><ns:SampleMode>250</ns:SampleMode><ns:SampleStd>45.816</ns:SampleStd><ns:Sample95thPct>245</ns:Sample95thPct><ns:NumBins>1</ns:NumBins><ns:BinCounts><ns:BinCount>11</ns:BinCount></ns:BinCounts><ns:BinWidth>500</ns:BinWidth><ns:MinOutlierValue>0</ns:MinOutlierValue><ns:MinBinValue>0</ns:MinBinValue><ns:MaxBinValue>500</ns:MaxBinValue><ns:MaxOutlierValue>0</ns:MaxOutlierValue><ns:MetricDescription>Number of Unfiltered Basecalls</ns:MetricDescription></NumUnfilteredBasecallsDist><ReadLenDist><ns:SampleSize>11</ns:SampleSize><ns:SampleMean>165.727</ns:SampleMean><ns:SampleMed>177</ns:SampleMed><ns:SampleMode>250</ns:SampleMode><ns:SampleStd>45.816</ns:SampleStd><ns:Sample95thPct>245</ns:Sample95thPct><ns:SampleN50>179</ns:SampleN50><ns:NumBins>1</ns:NumBins><ns:BinCounts><ns:BinCount>11</ns:BinCount></ns:BinCounts><ns:BinWidth>500</ns:BinWidth><ns:MinOutlierValue>0</ns:MinOutlierValue><ns:MinBinValue>0</ns:MinBinValue><ns:MaxBinValue>500</ns:MaxBinValue><ns:MaxOutlierValue>0</ns:MaxOutlierValue><ns:MetricDescription>Read Length</ns:MetricDescription></ReadLenDist><ReadQualDist><ns:SampleSize>11</ns:SampleSize><ns:SampleMean>0.8</ns:SampleMean><ns:SampleMed>0.8</ns:SampleMed><ns:SampleMode>0.81</ns:SampleMode><ns:SampleStd>5.37513e-08</ns:SampleStd><ns:Sample95thPct>0.8</ns:Sample95thPct><ns:NumBins>50</ns:NumBins><ns:BinCounts><ns:BinCount>0</ns:BinCount><ns:BinCount>0</ns:BinCount><ns:BinCount>0</ns:BinCount><ns:BinCount>0</ns:BinCount><ns:BinCount>0</ns:BinCount><ns:BinCount>0</ns:BinCount><ns:BinCount>0</ns:BinCount><ns:BinCount>0</ns:BinCount><ns:BinCount>0</ns:BinCount><ns:BinCount>0</ns:BinCount><ns:BinCount>0</ns:BinCount><ns:BinCount>0</ns:BinCount><ns:BinCount>0</ns:BinCount><ns:BinCount>0</ns:BinCount><ns:BinCount>0</ns:BinCount><ns:BinCount>0</ns:BinCount><ns:BinCount>0</ns:BinCount><ns:BinCount>0</ns:BinCount><ns:BinCount>0</ns:BinCount><ns:BinCount>0</ns:BinCount><ns:BinCount>0</ns:BinCount><ns:BinCount>0</ns:BinCount><ns:BinCount>0</ns:BinCount><ns:BinCount>0</ns:BinCount><ns:BinCount>0</ns:BinCount><ns:BinCount>0</ns:BinCount><ns:BinCount>0</ns:BinCount><ns:BinCount>0</ns:BinCount><ns:BinCount>0</ns:BinCount><ns:BinCount>0</ns:BinCount><ns:BinCount>0</ns:BinCount><ns:BinCount>0</ns:BinCount><ns:BinCount>0</ns:BinCount><ns:BinCount>0</ns:BinCount><ns:BinCount>0</ns:BinCount><ns:BinCount>0</ns:BinCount><ns:BinCount>0</ns:BinCount><ns:BinCount>0</ns:BinCount><ns:BinCount>0</ns:BinCount><ns:BinCount>0</ns:BinCount><ns:BinCount>11</ns:BinCount><ns:BinCount>0</ns:BinCount><ns:BinCount>0</ns:BinCount><ns:BinCount>0</ns:BinCount><ns:BinCount>0</ns:BinCount><ns:BinCount>0</ns:BinCount><ns:BinCount>0</ns:BinCount><ns:BinCount>0</ns:BinCount><ns:BinCount>0</ns:BinCount><ns:BinCount>0</ns:BinCount></ns:BinCounts><ns:BinWidth>0.02</ns:BinWidth><ns:MinOutlierValue>0</ns:MinOutlierValue><ns:MinBinValue>0</ns:MinBinValue><ns:MaxBinValue>1</ns:MaxBinValue><ns:MaxOutlierValue>0</ns:MaxOutlierValue><ns:MetricDescription>Read Quality</ns:MetricDescription></ReadQualDist><MovieReadQualDist><ns:SampleSize>11</ns:SampleSize><ns:SampleMean>0.8</ns:SampleMean><ns:SampleMed>0.8</ns:SampleMed><ns:SampleMode>0.81</ns:SampleMode><ns:SampleStd>5.37513e-08</ns:SampleStd><ns:Sample95thPct>0.8</ns:Sample95thPct><ns:NumBins>50</ns:NumBins><ns:BinCounts><ns:BinCount>0</ns:BinCount><ns:BinCount>0</ns:BinCount><ns:BinCount>0</ns:BinCount><ns:BinCount>0</ns:BinCount><ns:BinCount>0</ns:BinCount><ns:BinCount>0</ns:BinCount><ns:BinCount>0</ns:BinCount><ns:BinCount>0</ns:BinCount><ns:BinCount>0</ns:BinCount><ns:BinCount>0</ns:BinCount><ns:BinCount>0</ns:BinCount><ns:BinCount>0</ns:BinCount><ns:BinCount>0</ns:BinCount><ns:BinCount>0</ns:BinCount><ns:BinCount>0</ns:BinCount><ns:BinCount>0</ns:BinCount><ns:BinCount>0</ns:BinCount><ns:BinCount>0</ns:BinCount><ns:BinCount>0</ns:BinCount><ns:BinCount>0</ns:BinCount><ns:BinCount>0</ns:BinCount><ns:BinCount>0</ns:BinCount><ns:BinCount>0</ns:BinCount><ns:BinCount>0</ns:BinCount><ns:BinCount>0</ns:BinCount><ns:BinCount>0</ns:BinCount><ns:BinCount>0</ns:BinCount><ns:BinCount>0</ns:BinCount><ns:BinCount>0</ns:BinCount><ns:BinCount>0</ns:BinCount><ns:BinCount>0</ns:BinCount><ns:BinCount>0</ns:BinCount><ns:BinCount>0</ns:BinCount><ns:BinCount>0</ns:BinCount><ns:BinCount>0</ns:BinCount><ns:BinCount>0</ns:BinCount><ns:BinCount>0</ns:BinCount><ns:BinCount>0</ns:BinCount><ns:BinCount>0</ns:BinCount><ns:BinCount>0</ns:BinCount><ns:BinCount>11</ns:BinCount><ns:BinCount>0</ns:BinCount><ns:BinCount>0</ns:BinCount><ns:BinCount>0</ns:BinCount><ns:BinCount>0</ns:BinCount><ns:BinCount>0</ns:BinCount><ns:BinCount>0</ns:BinCount><ns:BinCount>0</ns:BinCount><ns:BinCount>0</ns:BinCount><ns:BinCount>0</ns:BinCount></ns:BinCounts><ns:BinWidth>0.02</ns:BinWidth><ns:MinOutlierValue>0</ns:MinOutlierValue><ns:MinBinValue>0</ns:MinBinValue><ns:MaxBinValue>1</ns:MaxBinValue><ns:MaxOutlierValue>0</ns:MaxOutlierValue><ns:MetricDescription>Movie Read Quality</ns:MetricDescription></MovieReadQualDist><InsertReadLenDist><ns:SampleSize>11</ns:SampleSize><ns:SampleMean>165.727</ns:SampleMean><ns:SampleMed>177</ns:SampleMed><ns:SampleMode>250</ns:SampleMode><ns:SampleStd>45.816</ns:SampleStd><ns:Sample95thPct>245</ns:Sample95thPct><ns:SampleN50>179</ns:SampleN50><ns:NumBins>1</ns:NumBins><ns:BinCounts><ns:BinCount>11</ns:BinCount></ns:BinCounts><ns:BinWidth>500</ns:BinWidth><ns:MinOutlierValue>0</ns:MinOutlierValue><ns:MinBinValue>0</ns:MinBinValue><ns:MaxBinValue>500</ns:MaxBinValue><ns:MaxOutlierValue>0</ns:MaxOutlierValue><ns:MetricDescription>Insert Read Length</ns:MetricDescription></InsertReadLenDist><InsertReadQualDist><ns:SampleSize>11</ns:SampleSize><ns:SampleMean>0</ns:SampleMean><ns:SampleMed>0</ns:SampleMed><ns:SampleMode>0.01</ns:SampleMode><ns:SampleStd>0</ns:SampleStd><ns:Sample95thPct>0</ns:Sample95thPct><ns:NumBins>50</ns:NumBins><ns:BinCounts><ns:BinCount>11</ns:BinCount><ns:BinCount>0</ns:BinCount><ns:BinCount>0</ns:BinCount><ns:BinCount>0</ns:BinCount><ns:BinCount>0</ns:BinCount><ns:BinCount>0</ns:BinCount><ns:BinCount>0</ns:BinCount><ns:BinCount>0</ns:BinCount><ns:BinCount>0</ns:BinCount><ns:BinCount>0</ns:BinCount><ns:BinCount>0</ns:BinCount><ns:BinCount>0</ns:BinCount><ns:BinCount>0</ns:BinCount><ns:BinCount>0</ns:BinCount><ns:BinCount>0</ns:BinCount><ns:BinCount>0</ns:BinCount><ns:BinCount>0</ns:BinCount><ns:BinCount>0</ns:BinCount><ns:BinCount>0</ns:BinCount><ns:BinCount>0</ns:BinCount><ns:BinCount>0</ns:BinCount><ns:BinCount>0</ns:BinCount><ns:BinCount>0</ns:BinCount><ns:BinCount>0</ns:BinCount><ns:BinCount>0</ns:BinCount><ns:BinCount>0</ns:BinCount><ns:BinCount>0</ns:BinCount><ns:BinCount>0</ns:BinCount><ns:BinCount>0</ns:BinCount><ns:BinCount>0</ns:BinCount><ns:BinCount>0</ns:BinCount><ns:BinCount>0</ns:BinCount><ns:BinCount>0</ns:BinCount><ns:BinCount>0</ns:BinCount><ns:BinCount>0</ns:BinCount><ns:BinCount>0</ns:BinCount><ns:BinCount>0</ns:BinCount><ns:BinCount>0</ns:BinCount><ns:BinCount>0</ns:BinCount><ns:BinCount>0</ns:BinCount><ns:BinCount>0</ns:BinCount><ns:BinCount>0</ns:BinCount><ns:BinCount>0</ns:BinCount><ns:BinCount>0</ns:BinCount><ns:BinCount>0</ns:BinCount><ns:BinCount>0</ns:BinCount><ns:BinCount>0</ns:BinCount><ns:BinCount>0</ns:BinCount><ns:BinCount>0</ns:BinCount><ns:BinCount>0</ns:BinCount></ns:BinCounts><ns:BinWidth>0.02</ns:BinWidth><ns:MinOutlierValue>0</ns:MinOutlierValue><ns:MinBinValue>0</ns:MinBinValue><ns:MaxBinValue>1</ns:MaxBinValue><ns:MaxOutlierValue>0</ns:MaxOutlierValue><ns:MetricDescription>Insert Read Quality</ns:MetricDescription></InsertReadQualDist><HqBaseFractionDist><ns:SampleSize>11</ns:SampleSize><ns:SampleMean>1</ns:SampleMean><ns:SampleMed>1</ns:SampleMed><ns:SampleMode>1</ns:SampleMode><ns:SampleStd>0</ns:SampleStd><ns:Sample95thPct>1</ns:Sample95thPct><ns:NumBins>30</ns:NumBins><ns:BinCounts><ns:BinCount>0</ns:BinCount><ns:BinCount>0</ns:BinCount><ns:BinCount>0</ns:BinCount><ns:BinCount>0</ns:BinCount><ns:BinCount>0</ns:BinCount><ns:BinCount>0</ns:BinCount><ns:BinCount>0</ns:BinCount><ns:BinCount>0</ns:BinCount><ns:BinCount>0</ns:BinCount><ns:BinCount>0</ns:BinCount><ns:BinCount>0</ns:BinCount><ns:BinCount>0</ns:BinCount><ns:BinCount>0</ns:BinCount><ns:BinCount>0</ns:BinCount><ns:BinCount>0</ns:BinCount><ns:BinCount>0</ns:BinCount><ns:BinCount>0</ns:BinCount><ns:BinCount>0</ns:BinCount><ns:BinCount>0</ns:BinCount><ns:BinCount>0</ns:BinCount><ns:BinCount>0</ns:BinCount><ns:BinCount>0</ns:BinCount><ns:BinCount>0</ns:BinCount><ns:BinCount>0</ns:BinCount><ns:BinCount>0</ns:BinCount><ns:BinCount>0</ns:BinCount><ns:BinCount>0</ns:BinCount><ns:BinCount>0</ns:BinCount><ns:BinCount>0</ns:BinCount><ns:BinCount>0</ns:BinCount></ns:BinCounts><ns:BinWidth>0</ns:BinWidth><ns:MinOutlierValue>1</ns:MinOutlierValue><ns:MinBinValue>1</ns:MinBinValue><ns:MaxBinValue>1</ns:MaxBinValue><ns:MaxOutlierValue>1</ns:MaxOutlierValue><ns:MetricDescription>Fraction of Bases in HQ Region</ns:MetricDescription></HqBaseFractionDist><BaselineLevelSequencingDist Channel="A"><ns:SampleSize>8014671</ns:SampleSize><ns:SampleMean>8.89803</ns:SampleMean><ns:SampleMed>8</ns:SampleMed><ns:SampleMode>5.56347</ns:SampleMode><ns:SampleStd>4.87307</ns:SampleStd><ns:Sample95thPct>16.7656</ns:Sample95thPct><ns:NumBins>30</ns:NumBins><ns:BinCounts><ns:BinCount>3</ns:BinCount><ns:BinCount>9</ns:BinCount><ns:BinCount>8</ns:BinCount><ns:BinCount>4</ns:BinCount><ns:BinCount>21</ns:BinCount><ns:BinCount>90</ns:BinCount><ns:BinCount>376</ns:BinCount><ns:BinCount>456</ns:BinCount><ns:BinCount>545</ns:BinCount><ns:BinCount>613</ns:BinCount><ns:BinCount>16095</ns:BinCount><ns:BinCount>164050</ns:BinCount><ns:BinCount>718381</ns:BinCount><ns:BinCount>1591925</ns:BinCount><ns:BinCount>1509826</ns:BinCount><ns:BinCount>1219016</ns:BinCount><ns:BinCount>911526</ns:BinCount><ns:BinCount>649709</ns:BinCount><ns:BinCount>450067</ns:BinCount><ns:BinCount>295117</ns:BinCount><ns:BinCount>188617</ns:BinCount><ns:BinCount>118538</ns:BinCount><ns:BinCount>71318</ns:BinCount><ns:BinCount>40597</ns:BinCount><ns:BinCount>22889</ns:BinCount><ns:BinCount>13130</ns:BinCount><ns:BinCount>8227</ns:BinCount><ns:BinCount>5313</ns:BinCount><ns:BinCount>3640</ns:BinCount><ns:BinCount>2634</ns:BinCount></ns:BinCounts><ns:BinWidth>1.62436</ns:BinWidth><ns:MinOutlierValue>-109.625</ns:MinOutlierValue><ns:MinBinValue>-16.3653</ns:MinBinValue><ns:MaxBinValue>32.3653</ns:MaxBinValue><ns:MaxOutlierValue>1388</ns:MaxOutlierValue><ns:MetricDescription>Baseline Level Sequencing Zmws: Channel A</ns:MetricDescription></BaselineLevelSequencingDist><BaselineLevelSequencingDist Channel="C"><ns:SampleSize>8014671</ns:SampleSize><ns:SampleMean>8.89803</ns:SampleMean><ns:SampleMed>8</ns:SampleMed><ns:SampleMode>5.56347</ns:SampleMode><ns:SampleStd>4.87307</ns:SampleStd><ns:Sample95thPct>16.7656</ns:Sample95thPct><ns:NumBins>30</ns:NumBins><ns:BinCounts><ns:BinCount>3</ns:BinCount><ns:BinCount>9</ns:BinCount><ns:BinCount>8</ns:BinCount><ns:BinCount>4</ns:BinCount><ns:BinCount>21</ns:BinCount><ns:BinCount>90</ns:BinCount><ns:BinCount>376</ns:BinCount><ns:BinCount>456</ns:BinCount><ns:BinCount>545</ns:BinCount><ns:BinCount>613</ns:BinCount><ns:BinCount>16095</ns:BinCount><ns:BinCount>164050</ns:BinCount><ns:BinCount>718381</ns:BinCount><ns:BinCount>1591925</ns:BinCount><ns:BinCount>1509826</ns:BinCount><ns:BinCount>1219016</ns:BinCount><ns:BinCount>911526</ns:BinCount><ns:BinCount>649709</ns:BinCount><ns:BinCount>450067</ns:BinCount><ns:BinCount>295117</ns:BinCount><ns:BinCount>188617</ns:BinCount><ns:BinCount>118538</ns:BinCount><ns:BinCount>71318</ns:BinCount><ns:BinCount>40597</ns:BinCount><ns:BinCount>22889</ns:BinCount><ns:BinCount>13130</ns:BinCount><ns:BinCount>8227</ns:BinCount><ns:BinCount>5313</ns:BinCount><ns:BinCount>3640</ns:BinCount><ns:BinCount>2634</ns:BinCount></ns:BinCounts><ns:BinWidth>1.62436</ns:BinWidth><ns:MinOutlierValue>-109.625</ns:MinOutlierValue><ns:MinBinValue>-16.3653</ns:MinBinValue><ns:MaxBinValue>32.3653</ns:MaxBinValue><ns:MaxOutlierValue>1388</ns:MaxOutlierValue><ns:MetricDescription>Baseline Level Sequencing Zmws: Channel C</ns:MetricDescription></BaselineLevelSequencingDist><BaselineLevelSequencingDist Channel="G"><ns:SampleSize>8014671</ns:SampleSize><ns:SampleMean>8.89803</ns:SampleMean><ns:SampleMed>8</ns:SampleMed><ns:SampleMode>5.56347</ns:SampleMode><ns:SampleStd>4.87307</ns:SampleStd><ns:Sample95thPct>16.7656</ns:Sample95thPct><ns:NumBins>30</ns:NumBins><ns:BinCounts><ns:BinCount>3</ns:BinCount><ns:BinCount>9</ns:BinCount><ns:BinCount>8</ns:BinCount><ns:BinCount>4</ns:BinCount><ns:BinCount>21</ns:BinCount><ns:BinCount>90</ns:BinCount><ns:BinCount>376</ns:BinCount><ns:BinCount>456</ns:BinCount><ns:BinCount>545</ns:BinCount><ns:BinCount>613</ns:BinCount><ns:BinCount>16095</ns:BinCount><ns:BinCount>164050</ns:BinCount><ns:BinCount>718381</ns:BinCount><ns:BinCount>1591925</ns:BinCount><ns:BinCount>1509826</ns:BinCount><ns:BinCount>1219016</ns:BinCount><ns:BinCount>911526</ns:BinCount><ns:BinCount>649709</ns:BinCount><ns:BinCount>450067</ns:BinCount><ns:BinCount>295117</ns:BinCount><ns:BinCount>188617</ns:BinCount><ns:BinCount>118538</ns:BinCount><ns:BinCount>71318</ns:BinCount><ns:BinCount>40597</ns:BinCount><ns:BinCount>22889</ns:BinCount><ns:BinCount>13130</ns:BinCount><ns:BinCount>8227</ns:BinCount><ns:BinCount>5313</ns:BinCount><ns:BinCount>3640</ns:BinCount><ns:BinCount>2634</ns:BinCount></ns:BinCounts><ns:BinWidth>1.62436</ns:BinWidth><ns:MinOutlierValue>-109.625</ns:MinOutlierValue><ns:MinBinValue>-16.3653</ns:MinBinValue><ns:MaxBinValue>32.3653</ns:MaxBinValue><ns:MaxOutlierValue>1388</ns:MaxOutlierValue><ns:MetricDescription>Baseline Level Sequencing Zmws: Channel G</ns:MetricDescription></BaselineLevelSequencingDist><BaselineLevelSequencingDist Channel="T"><ns:SampleSize>8014671</ns:SampleSize><ns:SampleMean>8.89803</ns:SampleMean><ns:SampleMed>8</ns:SampleMed><ns:SampleMode>5.56347</ns:SampleMode><ns:SampleStd>4.87307</ns:SampleStd><ns:Sample95thPct>16.7656</ns:Sample95thPct><ns:NumBins>30</ns:NumBins><ns:BinCounts><ns:BinCount>3</ns:BinCount><ns:BinCount>9</ns:BinCount><ns:BinCount>8</ns:BinCount><ns:BinCount>4</ns:BinCount><ns:BinCount>21</ns:BinCount><ns:BinCount>90</ns:BinCount><ns:BinCount>376</ns:BinCount><ns:BinCount>456</ns:BinCount><ns:BinCount>545</ns:BinCount><ns:BinCount>613</ns:BinCount><ns:BinCount>16095</ns:BinCount><ns:BinCount>164050</ns:BinCount><ns:BinCount>718381</ns:BinCount><ns:BinCount>1591925</ns:BinCount><ns:BinCount>1509826</ns:BinCount><ns:BinCount>1219016</ns:BinCount><ns:BinCount>911526</ns:BinCount><ns:BinCount>649709</ns:BinCount><ns:BinCount>450067</ns:BinCount><ns:BinCount>295117</ns:BinCount><ns:BinCount>188617</ns:BinCount><ns:BinCount>118538</ns:BinCount><ns:BinCount>71318</ns:BinCount><ns:BinCount>40597</ns:BinCount><ns:BinCount>22889</ns:BinCount><ns:BinCount>13130</ns:BinCount><ns:BinCount>8227</ns:BinCount><ns:BinCount>5313</ns:BinCount><ns:BinCount>3640</ns:BinCount><ns:BinCount>2634</ns:BinCount></ns:BinCounts><ns:BinWidth>1.62436</ns:BinWidth><ns:MinOutlierValue>-109.625</ns:MinOutlierValue><ns:MinBinValue>-16.3653</ns:MinBinValue><ns:MaxBinValue>32.3653</ns:MaxBinValue><ns:MaxOutlierValue>1388</ns:MaxOutlierValue><ns:MetricDescription>Baseline Level Sequencing Zmws: Channel T</ns:MetricDescription></BaselineLevelSequencingDist><DmeAngleEstDist Channel="A"><ns:SampleSize>11</ns:SampleSize><ns:SampleMean>-1</ns:SampleMean><ns:SampleMed>-1</ns:SampleMed><ns:SampleMode>-1</ns:SampleMode><ns:SampleStd>0</ns:SampleStd><ns:Sample95thPct>-1</ns:Sample95thPct><ns:NumBins>30</ns:NumBins><ns:BinCounts><ns:BinCount>0</ns:BinCount><ns:BinCount>0</ns:BinCount><ns:BinCount>0</ns:BinCount><ns:BinCount>0</ns:BinCount><ns:BinCount>0</ns:BinCount><ns:BinCount>0</ns:BinCount><ns:BinCount>0</ns:BinCount><ns:BinCount>0</ns:BinCount><ns:BinCount>0</ns:BinCount><ns:BinCount>0</ns:BinCount><ns:BinCount>0</ns:BinCount><ns:BinCount>0</ns:BinCount><ns:BinCount>0</ns:BinCount><ns:BinCount>0</ns:BinCount><ns:BinCount>0</ns:BinCount><ns:BinCount>0</ns:BinCount><ns:BinCount>0</ns:BinCount><ns:BinCount>0</ns:BinCount><ns:BinCount>0</ns:BinCount><ns:BinCount>0</ns:BinCount><ns:BinCount>0</ns:BinCount><ns:BinCount>0</ns:BinCount><ns:BinCount>0</ns:BinCount><ns:BinCount>0</ns:BinCount><ns:BinCount>0</ns:BinCount><ns:BinCount>0</ns:BinCount><ns:BinCount>0</ns:BinCount><ns:BinCount>0</ns:BinCount><ns:BinCount>0</ns:BinCount><ns:BinCount>0</ns:BinCount></ns:BinCounts><ns:BinWidth>0</ns:BinWidth><ns:MinOutlierValue>-1</ns:MinOutlierValue><ns:MinBinValue>-1</ns:MinBinValue><ns:MaxBinValue>-1</ns:MaxBinValue><ns:MaxOutlierValue>-1</ns:MaxOutlierValue><ns:MetricDescription>DME Angle Estimation: Analog A</ns:MetricDescription></DmeAngleEstDist><DmeAngleEstDist Channel="C"><ns:SampleSize>11</ns:SampleSize><ns:SampleMean>-1</ns:SampleMean><ns:SampleMed>-1</ns:SampleMed><ns:SampleMode>-1</ns:SampleMode><ns:SampleStd>0</ns:SampleStd><ns:Sample95thPct>-1</ns:Sample95thPct><ns:NumBins>30</ns:NumBins><ns:BinCounts><ns:BinCount>0</ns:BinCount><ns:BinCount>0</ns:BinCount><ns:BinCount>0</ns:BinCount><ns:BinCount>0</ns:BinCount><ns:BinCount>0</ns:BinCount><ns:BinCount>0</ns:BinCount><ns:BinCount>0</ns:BinCount><ns:BinCount>0</ns:BinCount><ns:BinCount>0</ns:BinCount><ns:BinCount>0</ns:BinCount><ns:BinCount>0</ns:BinCount><ns:BinCount>0</ns:BinCount><ns:BinCount>0</ns:BinCount><ns:BinCount>0</ns:BinCount><ns:BinCount>0</ns:BinCount><ns:BinCount>0</ns:BinCount><ns:BinCount>0</ns:BinCount><ns:BinCount>0</ns:BinCount><ns:BinCount>0</ns:BinCount><ns:BinCount>0</ns:BinCount><ns:BinCount>0</ns:BinCount><ns:BinCount>0</ns:BinCount><ns:BinCount>0</ns:BinCount><ns:BinCount>0</ns:BinCount><ns:BinCount>0</ns:BinCount><ns:BinCount>0</ns:BinCount><ns:BinCount>0</ns:BinCount><ns:BinCount>0</ns:BinCount><ns:BinCount>0</ns:BinCount><ns:BinCount>0</ns:BinCount></ns:BinCounts><ns:BinWidth>0</ns:BinWidth><ns:MinOutlierValue>-1</ns:MinOutlierValue><ns:MinBinValue>-1</ns:MinBinValue><ns:MaxBinValue>-1</ns:MaxBinValue><ns:MaxOutlierValue>-1</ns:MaxOutlierValue><ns:MetricDescription>DME Angle Estimation: Analog C</ns:MetricDescription></DmeAngleEstDist><DmeAngleEstDist Channel="G"><ns:SampleSize>11</ns:SampleSize><ns:SampleMean>-1</ns:SampleMean><ns:SampleMed>-1</ns:SampleMed><ns:SampleMode>-1</ns:SampleMode><ns:SampleStd>0</ns:SampleStd><ns:Sample95thPct>-1</ns:Sample95thPct><ns:NumBins>30</ns:NumBins><ns:BinCounts><ns:BinCount>0</ns:BinCount><ns:BinCount>0</ns:BinCount><ns:BinCount>0</ns:BinCount><ns:BinCount>0</ns:BinCount><ns:BinCount>0</ns:BinCount><ns:BinCount>0</ns:BinCount><ns:BinCount>0</ns:BinCount><ns:BinCount>0</ns:BinCount><ns:BinCount>0</ns:BinCount><ns:BinCount>0</ns:BinCount><ns:BinCount>0</ns:BinCount><ns:BinCount>0</ns:BinCount><ns:BinCount>0</ns:BinCount><ns:BinCount>0</ns:BinCount><ns:BinCount>0</ns:BinCount><ns:BinCount>0</ns:BinCount><ns:BinCount>0</ns:BinCount><ns:BinCount>0</ns:BinCount><ns:BinCount>0</ns:BinCount><ns:BinCount>0</ns:BinCount><ns:BinCount>0</ns:BinCount><ns:BinCount>0</ns:BinCount><ns:BinCount>0</ns:BinCount><ns:BinCount>0</ns:BinCount><ns:BinCount>0</ns:BinCount><ns:BinCount>0</ns:BinCount><ns:BinCount>0</ns:BinCount><ns:BinCount>0</ns:BinCount><ns:BinCount>0</ns:BinCount><ns:BinCount>0</ns:BinCount></ns:BinCounts><ns:BinWidth>0</ns:BinWidth><ns:MinOutlierValue>-1</ns:MinOutlierValue><ns:MinBinValue>-1</ns:MinBinValue><ns:MaxBinValue>-1</ns:MaxBinValue><ns:MaxOutlierValue>-1</ns:MaxOutlierValue><ns:MetricDescription>DME Angle Estimation: Analog G</ns:MetricDescription></DmeAngleEstDist><DmeAngleEstDist Channel="T"><ns:SampleSize>11</ns:SampleSize><ns:SampleMean>-1</ns:SampleMean><ns:SampleMed>-1</ns:SampleMed><ns:SampleMode>-1</ns:SampleMode><ns:SampleStd>0</ns:SampleStd><ns:Sample95thPct>-1</ns:Sample95thPct><ns:NumBins>30</ns:NumBins><ns:BinCounts><ns:BinCount>0</ns:BinCount><ns:BinCount>0</ns:BinCount><ns:BinCount>0</ns:BinCount><ns:BinCount>0</ns:BinCount><ns:BinCount>0</ns:BinCount><ns:BinCount>0</ns:BinCount><ns:BinCount>0</ns:BinCount><ns:BinCount>0</ns:BinCount><ns:BinCount>0</ns:BinCount><ns:BinCount>0</ns:BinCount><ns:BinCount>0</ns:BinCount><ns:BinCount>0</ns:BinCount><ns:BinCount>0</ns:BinCount><ns:BinCount>0</ns:BinCount><ns:BinCount>0</ns:BinCount><ns:BinCount>0</ns:BinCount><ns:BinCount>0</ns:BinCount><ns:BinCount>0</ns:BinCount><ns:BinCount>0</ns:BinCount><ns:BinCount>0</ns:BinCount><ns:BinCount>0</ns:BinCount><ns:BinCount>0</ns:BinCount><ns:BinCount>0</ns:BinCount><ns:BinCount>0</ns:BinCount><ns:BinCount>0</ns:BinCount><ns:BinCount>0</ns:BinCount><ns:BinCount>0</ns:BinCount><ns:BinCount>0</ns:BinCount><ns:BinCount>0</ns:BinCount><ns:BinCount>0</ns:BinCount></ns:BinCounts><ns:BinWidth>0</ns:BinWidth><ns:MinOutlierValue>-1</ns:MinOutlierValue><ns:MinBinValue>-1</ns:MinBinValue><ns:MaxBinValue>-1</ns:MaxBinValue><ns:MaxOutlierValue>-1</ns:MaxOutlierValue><ns:MetricDescription>DME Angle Estimation: Analog T</ns:MetricDescription></DmeAngleEstDist><SequencingUmy>1823</SequencingUmy></PipeStats>